pipeline_optimizer/__init__.py
pipeline_optimizer/transformers.py
pipeline_optimizer-0.1.7.dist-info/LICENSE
pipeline_optimizer-0.1.7.dist-info/METADATA
pipeline_optimizer-0.1.7.dist-info/WHEEL
pipeline_optimizer-0.1.7.dist-info/RECORD
