Metadata-Version: 2.1
Name: pipeline-optimizer
Version: 0.1.7
Summary: Pipeline Optimizer is a Python library that aims to simplify and automate the machine learning pipeline, from preprocessing and testing to deployment. By providing a reusable infrastructure, the library allows you to manage custom preprocessing functions and reuse them effortlessly during the deployment of your project. This is particularly useful when dealing with a large number of custom functions.
License: MIT
Author: Stanislav Kharchenko
Requires-Python: >=3.8,<4.0
Classifier: License :: OSI Approved :: MIT License
Classifier: Programming Language :: Python :: 3
Classifier: Programming Language :: Python :: 3.8
Classifier: Programming Language :: Python :: 3.9
Classifier: Programming Language :: Python :: 3.10
Classifier: Programming Language :: Python :: 3.11
Requires-Dist: pandas (>=2.0.0,<3.0.0)
Requires-Dist: scikit-learn (>=0.24.0,<0.25.0)
